LICENSE
README.md
setup.cfg
setup.py
screwdriver_cd_python_sdk/__init__.py
screwdriver_cd_python_sdk/events.py
screwdriver_cd_python_sdk/pipeline.py
screwdriver_cd_python_sdk/screwdriver_initializer.py
screwdriver_cd_python_sdk/secrets.py
screwdriver_cd_python_sdk.egg-info/PKG-INFO
screwdriver_cd_python_sdk.egg-info/SOURCES.txt
screwdriver_cd_python_sdk.egg-info/dependency_links.txt
screwdriver_cd_python_sdk.egg-info/not-zip-safe
screwdriver_cd_python_sdk.egg-info/top_level.txt