Metadata-Version: 2.1
Name: screwdriver-cd-python-sdk
Version: 1.0.14
Summary: Screwdriver CD Python Software Development Kit (SDK) for managing resources in Screwdriver
Home-page: https://github.com/QubitPi/screwdriver-cd-python-sdk
Author: Jiaqi liu
Author-email: jack20220723@gmail.com
License: Apache-2.0
Requires-Python: >=3.10
License-File: LICENSE
